llm_comparator/_colab.py
llm_comparator/_logging.py
llm_comparator/comparison.py
llm_comparator/llm_judge_runner.py
llm_comparator/model_helper.py
llm_comparator/prompt_templates.py
llm_comparator/rationale_bullet_generator.py
llm_comparator/rationale_cluster_generator.py
llm_comparator/types.py
llm_comparator/utils.py
llm_comparator/utils_test.py
llm_comparator/data/dev_sources.concat.js
llm_comparator/data/index.html
llm_comparator/data/static/favicon.svg
llm_comparator-0.1.dist-info/LICENSE
llm_comparator-0.1.dist-info/METADATA
llm_comparator-0.1.dist-info/WHEEL
llm_comparator-0.1.dist-info/top_level.txt
llm_comparator-0.1.dist-info/RECORD
