Metadata-Version: 2.1
Name: llm-comparator
Version: 0.1
Summary: LLM Comparator: An interactive visualization tool for side-by-side LLM evaluation
Author: Google, LLC
License: 
Project-URL: Homepage, https://github.com/PAIR-code/llm-comparator
Project-URL: Repository, https://github.com/PAIR-code/llm-comparator
Project-URL: Bug Tracker, https://github.com/PAIR-code/llm-comparator/issues
Project-URL: Demo, https://pair-code.github.io/llm-comparator/
Keywords: model evaluation,large language models,artifical intelligence,machine learning
Classifier: Development Status :: 4 - Beta
Classifier: Intended Audience :: Developers
Classifier: Intended Audience :: Science/Research
Classifier: License :: OSI Approved :: Apache Software License
Classifier: Operating System :: OS Independent
Classifier: Programming Language :: Python :: 3 :: Only
Classifier: Programming Language :: Python :: 3.10
Classifier: Topic :: Scientific/Engineering :: Artificial Intelligence
Classifier: Topic :: Scientific/Engineering :: Information Analysis
Classifier: Topic :: Scientific/Engineering :: Visualization
Classifier: Typing :: Typed
Requires-Python: >=3.9
License-File: LICENSE
Requires-Dist: absl-py
Requires-Dist: numpy
Requires-Dist: tqdm
Requires-Dist: vertexai
